setup.cfg
setup.py
ZaidPK/ZaidPK.py
ZaidPK/__init__.py
ZaidPK.egg-info/PKG-INFO
ZaidPK.egg-info/SOURCES.txt
ZaidPK.egg-info/dependency_links.txt
ZaidPK.egg-info/not-zip-safe
ZaidPK.egg-info/top_level.txt