Metadata-Version: 2.1
Name: ZaidPK
Version: 0.2
Summary: THE KING PYTHON PRO
Home-page: UNKNOWN
Author: ZaidPytele
Author-email: fhdhasd39@gmail.com
License: UNKNOWN
Platform: UNKNOWN
Classifier: Programming Language :: Python :: 3
Classifier: Operating System :: OS Independent
Classifier: License :: OSI Approved :: MIT License
